{
  "stringKey": "Hodnota řetězce",
  "trainingTitle": "Název školení",
  "trainingDescription": "Popis školení",
  "trainingDescriptionOptional": "Popis školení (volitelné)",
  "enterTheQuestion": "Zadejte otázku.",
  "enterTheChoice": "Zadejte svou volbu.",
  "option": "Možnost {0}",
  "dueIn": " Termín splnění: {0} {1}",
  "addMoreOptions": "Přidat možnosti",
  "choices": "Volby",
  "checkMe": "Zkontrolovat, jestli je to správně",
  "next": "Další",
  "back": "Zpět",
  "required": "Povinné",
  "dueBy": "Termín",
  "resultVisibleTo": "Výsledky uvidí:",
  "resultEveryone": "Výsledky uvidí všichni",
  "resultMe": "Výsledky uvidím pouze já",
  "correctAnswer": "Správná odpověď",
  "everyone": "Všichni",
  "onlyMe": "Jen já",
  "showCorrectAnswer": "Po každé otázce zobrazit správnou odpověď",
  "answerCannotChange": "Pokud vyberete tuto možnost, nepůjde změnit odpovědi.",
  "question": "Otázka",
  "questions": "Otázky",
  "question_numbers": "Otázky: {0}",
  "totalQuestionTraining": "Školení má celkem {0} {1}.",
  "completeTraining": "Dokončit školení",
  "alreadyTired": "Poznámka: Tohle školení jste už absolvovali.",
  "you": "Vy",
  "multipleAttemptNo": "Tohle školení jste už absolvovali. Je povolený jen jeden pokus.",
  "multipleAttemptYes": "Tohle školení jste už absolvovali. Můžete to zkusit znova, ale skóre se neaktualizuje.",
  "notConsideredFinalScore": "Můžete zkusit školení znovu, abyste si ho procvičili. Skóre za tenhle pokus se do konečného skóre nezapočítá.",
  "start": "Začít",
  "uploadCoverImage": "Nahrát titulní obrázek",
  "xofy": "{0} z(e) {1}",
  "note": "Poznámka:",
  "choose_any_choice": "Odpovězte, abyste mohli přejít k další otázce.",
  "continue": "Pokračovat",
  "answer_response": "Reakce na odpověď",
  "correct": "Správně",
  "your_answer": "Vaše odpověď",
  "incorrect": "Špatně",
  "correct_answer": "Správná odpověď",
  "your_answer_is": "Vaše odpověď je",
  "right_answer_is": "Pravá odpověď je",
  "submit": "Odeslat",
  "training_summary": "Shrnutí školení",
  "training_expired": "Platnost školení vypršela.",
  "expiredOn": "Platnost vypršela",
  "participation": "Účast {0} %",
  "xofyPeopleResponded": "Počet odpovědí: {0} ze {1} lidí.",
  "you_responded": "Odpověděli jste",
  "score": "Skóre {0}",
  "youYetRespond": "Ještě jste neodpověděli.",
  "responders": "Respondenti",
  "nonResponders": "Nereagující uživatelé",
  "respond": "Odpovědět",
  "viewResult": "Zobrazit výsledek",
  "be_the_first_one_to_respond": "Buďte první, kdo se zúčastní školení.",
  "one_responded": "{0} odpověděl(a).",
  "two_responded": "Uživatelé {0} a {1} odpověděli.",
  "three_responded": "Uživatelé {0}, {1} a {2} odpověděli.",
  "three_and_one_other_responded": "Uživatelé {0}, {1}, {2} a 1 další odpověděli.",
  "three_and_others_responded": "Uživatelé {0}, {1}, {2} a další ({3}) odpověděli.",
  "due_by_date": "Termín: {0}",
  "result_everyone": "Odpovědi uvidí všichni",
  "result_creator": "Odpovědi vidí pouze odesílatel.",
  "photo": "Obrázek",
  "document": "Dokument",
  "video": "Video",
  "text": "Text",
  "quiz": "Kvíz",
  "done": "Hotovo",
  "correctChoice": "Vyberte správnou odpověď na otázku.",
  "atleastOneContent": "K vytvoření školení je potřeba alespoň jedna položka obsahu.",
  "tapUploadPhoto": "Nahrát obrázek",
  "questionLeftBlank": "Otázka nemůže zůstat prázdná.",
  "uploadPhoto": "Nahrát obrázek",
  "descriptionContentAbout": "Popis. O čem je obsah?",
  "question_with": "Otázka s {0} možnostmi",
  "changeDueDate": "Změnit termín splnění",
  "change": "Změnit",
  "cancel": "Zrušit",
  "discard": "Zahodit",
  "correct_answer_is": "Správná odpověď je",
  "notePleaseChooseChoice": "Než přejdete k další otázce, odpovězte.",
  "aggregrateResult": "Souhrnný výsledek",
  "training_title": "Název školení",
  "training_description": "Popis školení",
  "coverImage": "Titulní obrázek (nepovinný)",
  "clear": "Vymazat",
  "changeDueBy": "Změnit do",
  "closeTraining": "Zavřít školení",
  "close": "Zavřít",
  "ok": "OK",
  "confirm": "Potvrdit",
  "confirmDeleteMsg": "Opravdu chcete odstranit?",
  "confirmDeleteContentMsg": "Opravdu chcete zahodit tenhle obsah?",
  "deleteTraining": "Odstranit školení",
  "tapUploadImage": "Nahrát titulní obrázek",
  "tapUploadFile": "Nahrát dokument",
  "tapUploadVideo": "Nahrát video",
  "invalidFileFormat": "Neplatný formát souboru",
  "invalidFileSize": "Překročení limitu velikosti videa",
  "alert_invalid_date_time": "Upozornění! Neplatné datum nebo čas. Musí být větší než aktuální datum a čas.",
  "greater_current_date": "Musí být větší než aktuální datum a čas.",
  "twoOptionError": "Požadují se alespoň dvě možnosti.",
  "closeTrainingConfirm": "Opravdu chcete tohle školení zavřít?",
  "deleteTrainingConfirm": "Opravdu chcete tohle školení odstranit?",
  "alert": "Upozornění!",
  "maximum_images_allowed": "Je povoleno maximálně 10 obrázků najednou.",
  "atleastOneQuestion": "Minimálně jedna otázka je povinná.",
  "maximumTenOptions": "U otázky můžete uvést maximálně 10 možností.",
  "addContent": "Přidat obsah",
  "addQuestions": "Přidat otázky",
  "download": "Stáhnout",
  "downloadImage": "Stáhnout obrázek",
  "downloadCSV": "Stáhnout CSV",
  "allowMultipleAttemptKey": "Povolit více pokusů",
  "assigneeTakeMultipleTraining": "Pokud chcete povolit jen jeden pokus, zrušte zaškrtnutí.",
  "addTitlePlaceholder": "Přidat název obsahu",
  "addDescriptionPlaceholder": "O čem je obsah? (nepovinné)",
  "edit": "Upravit",
  "chooseAnyChoice": "Vyberte libovolnou volbu.",
  "answerResponse": "Reakce na odpověď",
  "yourAnswer": "Vaše odpověď",
  "yourAnswerIs": "Vaše odpověď je",
  "rightAnswerIs": "Správná odpověď je",
  "correctAnswerIs": "Správná odpověď je",
  "trainingSummary": "Shrnutí školení",
  "trainingExpired": "Platnost školení vypršela.",
  "trainingContent": "Obsah školení",
  "total": "Celkem",
  "trainingItems": "Položky školení",
  "previous": "Předchozí",
  "correctAnswerSetting": "{0} Po každé otázce se zobrazí správná odpověď.",
  "addTextDescriptionPlaceholder": "Přidat text",
  "contentLimitExceed": "Překročení limitu obsahu",
  "loadMore": "Načíst další…",
  "loadLess": "Menší zatížení",
  "nWeek": "{0} týden",
  "hours": "hod.",
  "hour": "hod.",
  "minutes": "min.",
  "minute": "min.",
  "days": "dny",
  "day": "den",
  "daysCalendar": "Neděle, Pondělí, Úterý, Středa, Čtvrtek, Pátek, Sobota",
  "daysShortCalendar": "Ne,Po,Út,St,Čt,Pá,So",
  "daysMinCalendar": "Ne, Po, Út, St, Čt, Pá, So",
  "monthsCalendar": "leden, únor, březen, duben, květen, červen, červenec, srpen, září, říjen, listopad, prosinec",
  "monthsShortCalendar": "Led, Úno, Bře, Dub, Kvě, Čvn, Čvc, Srp, Zář, Říj, Lis, Pro",
  "todayCalendar": "Dnes",
  "monthsTitleCalendar": "Měsíce",
  "clearCalendar": "Vymazat",
  "questionIsRequired": "Tato otázka je povinná.",
  "$manifest.description": "Publikovat školení",
  "$manifest.name": "Školení",
  "$manifest.msTeamsProps.name.full": "Školení",
  "$manifest.msTeamsProps.name.short": "Školení",
  "$manifest.msTeamsProps.description.full": "Publikujte školení pro svůj tým a připněte dokončení.",
  "$manifest.msTeamsProps.description.short": "Publikovat školení"
}