{
  "stringKey": "स्ट्रिंग मान",
  "trainingTitle": "प्रशिक्षण शीर्षक",
  "trainingDescription": "प्रशिक्षण वर्णन",
  "trainingDescriptionOptional": "प्रशिक्षण विवरण (वैकल्पिक)",
  "enterTheQuestion": "प्रश्न दर्ज करें",
  "enterTheChoice": "अपनी पसंद को दर्ज करें",
  "option": "विकल्प {0}",
  "dueIn": " {0}{1} में नियत",
  "addMoreOptions": "विकल्प जोड़ें",
  "choices": "विकल्प",
  "checkMe": "सही होने पर मुझे बताएँ",
  "next": "अगला",
  "back": "वापस जाएँ",
  "required": "आवश्यक",
  "dueBy": "तक देय",
  "resultVisibleTo": "के लिए परिणाम दृश्यमान है",
  "resultEveryone": "परिणाम सभी के लिए दृश्यमान",
  "resultMe": "केवल मेरे लिए दृश्यमान परिणाम",
  "correctAnswer": "सही उत्तर",
  "everyone": "सभी",
  "onlyMe": "केवल मैं",
  "showCorrectAnswer": "प्रत्येक प्रश्न के बाद सही उत्तर दिखाएँ",
  "answerCannotChange": "इस विकल्प के चयनित होने पर उत्तर बदले नहीं जा सकते",
  "question": "सवाल",
  "questions": "प्रश्न",
  "question_numbers": "प्रश्न: {0}",
  "totalQuestionTraining": "प्रशिक्षण में कुल {0} {1}",
  "completeTraining": "प्रशिक्षण पूर्ण करें",
  "alreadyTired": "नोट - आपने पहले ही इस प्रशिक्षण में भाग ले लिया है!",
  "you": "आप",
  "multipleAttemptNo": "आपने इस प्रशिक्षण को पहले ही पूरा कर लिया है. केवल एकल प्रयास की अनुमति है.",
  "multipleAttemptYes": "आपने इस प्रशिक्षण को पहले ही पूरा कर लिया है. आप दुबारा प्रयास कर सकते हैं लेकिन स्कोर का अद्यतन नहीं किया जाएगा.",
  "notConsideredFinalScore": "आप अभ्यास के लिए इस प्रशिक्षण का पुनर्प्रयास कर सकते हैं. इस प्रयास के लिए आपका स्कोर अंतिम स्कोर के तौर पर नहीं देखा जाएगा.",
  "start": "प्रारंभ करें",
  "uploadCoverImage": "कवर छव को अपलोड करें",
  "xofy": "{1} का {0}",
  "note": "नोट!",
  "choose_any_choice": "कृपया अगले प्रश्न पर जाने से पहले उत्तर दें",
  "continue": "जारी रखें",
  "answer_response": "उत्तर दिया गया",
  "correct": "सही",
  "your_answer": "आपका उत्तर",
  "incorrect": "गलत",
  "correct_answer": "सही उत्तर",
  "your_answer_is": "आपका उत्तर",
  "right_answer_is": "इसका सही उत्तर",
  "submit": "सबमिट करें",
  "training_summary": "प्रशिक्षण सारांश",
  "training_expired": "प्रशिक्षण की समय सीमा समाप्त...",
  "expiredOn": "समय सीमा समाप्ति",
  "participation": "भागीदारी {0}%",
  "xofyPeopleResponded": "{1} लोगों में से {0} ने प्रतिसाद दिया",
  "you_responded": "आपने उत्तर दिया",
  "score": "स्कोर{0}",
  "youYetRespond": "आपको प्रतिसाद देना शेष है",
  "responders": "प्रतिसाद देने वाले",
  "nonResponders": "प्रतिसाद न देने वाले",
  "respond": "प्रतिसाद दें",
  "viewResult": "परिणाम देखें",
  "be_the_first_one_to_respond": "प्रशिक्षण पूरा करने वाले पहले व्यक्ति बनें",
  "one_responded": "{0} ने प्रतिसाद दिया",
  "two_responded": "{0}और {1} ने प्रतिसाद दिया",
  "three_responded": "{0}, {1} और {2} ने प्रतिसाद दिया",
  "three_and_one_other_responded": "{0}, {1}, {2} और 1 अन्य ने प्रतिसाद दिया",
  "three_and_others_responded": "{0}, {1}, {2} और {3} अन्य ने प्रतिसाद दिया",
  "due_by_date": "{0} तक देय",
  "result_everyone": "प्रतिसाद सब के लिए दृश्यमान हैं",
  "result_creator": "केवल प्रेषक के लिए दृश्यमान परिणाम",
  "photo": "छवि",
  "document": "दस्तावेज़",
  "video": "वीडियो",
  "text": "पाठ",
  "quiz": "क्विज़",
  "done": "पूर्ण",
  "correctChoice": "कृपया प्रश्न के लिए सही विकल्प का चयन करें",
  "atleastOneContent": "प्रशिक्षण बनाने के लिए कम से कम एक सामग्री आइटम आवश्यक है",
  "tapUploadPhoto": "छवि अपलोड करें",
  "questionLeftBlank": "प्रश्न रिक्त नहीं छोड़ा जा सकता",
  "uploadPhoto": "छवि अपलोड करें",
  "descriptionContentAbout": "वर्णन. यह सामग्री किस बारे में है?",
  "question_with": "{0} विकल्पों वाला प्रश्न",
  "changeDueDate": "नियत दिनांक परिवर्तित करें",
  "change": "परिवर्तित करें",
  "cancel": "रद्द करें",
  "discard": "छोड़ें",
  "correct_answer_is": "सही उत्तर",
  "notePleaseChooseChoice": "कृपया अगले प्रश्न पर जाने से पहले उत्तर दें",
  "aggregrateResult": "कुल परिणाम",
  "training_title": "प्रशिक्षण शीर्षक",
  "training_description": "प्रशिक्षण वर्णन",
  "coverImage": "कवर छवि (वैकल्पिक)",
  "clear": "हटाएँ",
  "changeDueBy": "इसके द्वारा नियत परिवर्तन",
  "closeTraining": "प्रशिक्षण बंद करें",
  "close": "बंद करें",
  "ok": "ठीक",
  "confirm": "पुष्टि करें",
  "confirmDeleteMsg": "क्या आप वाकई हटाना चाहते हैं?",
  "confirmDeleteContentMsg": "क्या आप वाकई यह सामग्री हटाना चाहते हैं?",
  "deleteTraining": "प्रशिक्षण हटाएँ",
  "tapUploadImage": "कवर छव को अपलोड करें",
  "tapUploadFile": "दस्तावेज़ अपलोड करें",
  "tapUploadVideo": "वीडियो अपलोड करें",
  "invalidFileFormat": "फ़ाइल स्वरूप अमान्य है",
  "invalidFileSize": "वीडियो आकार सीमा से अधिक",
  "alert_invalid_date_time": "चेतावनी! दिनांक या समय अमान्य है! यह वर्तमान दिनांक और समय से आगे का होना चाहिए.",
  "greater_current_date": "यह वर्तमान दिनांक और समय से आगे का होना चाहिए.",
  "twoOptionError": "कम से कम दो विकल्प आवश्यक हैं",
  "closeTrainingConfirm": "क्या आप वाकई इस प्रशिक्षण को बंद करना चाहते हैं?",
  "deleteTrainingConfirm": "क्या आप वाक़ई इस प्रशिक्षण को हटाना चाहते हैं?",
  "alert": "चेतावनी!",
  "maximum_images_allowed": "एक समय में अधिकतम 10 छवियाँ अनुमत हैं",
  "atleastOneQuestion": "कम से कम एक प्रश्न करें.",
  "maximumTenOptions": "किसी प्रश्न के लिए अधिकतम 10 विकल्पों की अनुमति है.",
  "addContent": "सामग्री जोड़ें",
  "addQuestions": "प्रश्नों को जोड़ें",
  "download": "डाउनलोड करें",
  "downloadImage": "छवि डाउनलोड करें",
  "downloadCSV": "CSV डाउनलोड करें",
  "allowMultipleAttemptKey": "एकाधिक प्रयासों की अनुमति दें",
  "assigneeTakeMultipleTraining": "केवल एकल प्रयास की अनुमति देने के लिए अनचेक करें.",
  "addTitlePlaceholder": "सामग्री का शीर्षक जोड़ें",
  "addDescriptionPlaceholder": "यह सामग्री किस बारे में है? (वैकल्पिक)",
  "edit": "संपादित करें",
  "chooseAnyChoice": "कृपया कोई भी पसंद चुनें",
  "answerResponse": "प्रतिसाद का उत्तर दें",
  "yourAnswer": "आपका उत्तर",
  "yourAnswerIs": "आपका उत्तर",
  "rightAnswerIs": "इसका सही उत्तर",
  "correctAnswerIs": "सही उत्तर",
  "trainingSummary": "प्रशिक्षण सारांश",
  "trainingExpired": "प्रशिक्षण की समय सीमा समाप्त...",
  "trainingContent": "प्रशिक्षण सामग्री",
  "total": "कुल",
  "trainingItems": "प्रशिक्षण आइटम",
  "previous": "पिछला",
  "correctAnswerSetting": "हर प्रश्न के बाद दिखाया गया {0} सही उत्तर",
  "addTextDescriptionPlaceholder": "पाठ जोड़ें",
  "contentLimitExceed": "सामग्री सीमा से अधिक हो गई है",
  "loadMore": "अधिक लोड करें...",
  "loadLess": "कम लोड करें",
  "nWeek": "{0} सप्ताह",
  "hours": "घंटे",
  "hour": "घंटा",
  "minutes": "मिनट",
  "minute": "मिनट",
  "days": "दिन",
  "day": "दिन",
  "daysCalendar": "रविवार, सोमवार, मंगलवार, बुधवार, गुरुवार, शुक्रवार, शनिवार",
  "daysShortCalendar": "रवि, सोम, मंगल, बुध, गुरु, शुक्र, शनि",
  "daysMinCalendar": "र, सो, मं, बु, गु, शु, श",
  "monthsCalendar": "जनवरी, फरवरी, मार्च, अप्रैल, मई, जून, जुलाई, अगस्त, सितंबर, अक्टूबर, नवंबर, दिसंबर",
  "monthsShortCalendar": "जन, फर, मार्च, अप्रै, मई, जून, जुला, अग, सितं, अक्टू, नवं, दिसं",
  "todayCalendar": "आज",
  "monthsTitleCalendar": "माह",
  "clearCalendar": "साफ करें",
  "questionIsRequired": "यह प्रश्न आवश्यक है",
  "$manifest.description": "प्रशिक्षण प्रकाशित करें",
  "$manifest.name": "प्रशिक्षण",
  "$manifest.msTeamsProps.name.full": "प्रशिक्षण",
  "$manifest.msTeamsProps.name.short": "प्रशिक्षण",
  "$manifest.msTeamsProps.description.full": "अपनी टीम के लिए प्रशिक्षण प्रकाशित करें और पूर्ण होने की स्थिति ट्रैक करें",
  "$manifest.msTeamsProps.description.short": "प्रशिक्षण प्रकाशित करें"
}